iplist/__init__.py
iplist/main.py
iplist-0.0.2.dist-info/LICENSE
iplist-0.0.2.dist-info/METADATA
iplist-0.0.2.dist-info/WHEEL
iplist-0.0.2.dist-info/entry_points.txt
iplist-0.0.2.dist-info/top_level.txt
iplist-0.0.2.dist-info/RECORD
