Metadata-Version: 2.1
Name: iplist
Version: 0.0.2
Summary: Expand ip ranges to list of ips
Home-page: https://gitlab.com/Zer1t0/iplist
Author: Eloy Perez
Author-email: zer1t0ps@protonmail.com
License: UNKNOWN
Platform: UNKNOWN
Classifier: Programming Language :: Python :: 3
Classifier: License :: OSI Approved :: GNU General Public License v3 (GPLv3)
